minud/__init__.py
minud/mito_segmentator.py
minud-1.0.6.dist-info/LICENSE
minud-1.0.6.dist-info/METADATA
minud-1.0.6.dist-info/WHEEL
minud-1.0.6.dist-info/top_level.txt
minud-1.0.6.dist-info/RECORD
