Metadata-Version: 2.1
Name: minud
Version: 1.0.6
Summary: MiNuD: a tool for the analysis of Mitochondrial Nucleoids Distribution
Author-email: Gonzalo Vidal <g.a.vidal-pena2@ncl.ac.uk>
Maintainer-email: Gonzalo Vidal <g.a.vidal-pena2@ncl.ac.uk>
License: MIT License
Project-URL: Homepage, https://github.com/RudgeLab/MiNuD
Project-URL: Bug Tracker, https://github.com/RudgeLab/MiNuD/issues
Keywords: mitochondria,data,analysis,nucleoids,distribution
Classifier: Programming Language :: Python :: 3
Classifier: License :: OSI Approved :: MIT License
Classifier: Operating System :: OS Independent
Requires-Python: >=3
License-File: LICENSE
Requires-Dist: numpy
Requires-Dist: scipy
Requires-Dist: pandas
Requires-Dist: matplotlib
Requires-Dist: seaborn
Requires-Dist: scikit-image
Requires-Dist: openpyxl
Provides-Extra: test
Requires-Dist: pytest <5.0.0 ; extra == 'test'
Requires-Dist: pytest-cov[all] ; extra == 'test'
